mcp_superiorapis/__init__.py
mcp_superiorapis/server.py
mcp_superiorapis-1.1.9.dist-info/METADATA
mcp_superiorapis-1.1.9.dist-info/WHEEL
mcp_superiorapis-1.1.9.dist-info/entry_points.txt
mcp_superiorapis-1.1.9.dist-info/RECORD
