Metadata-Version: 2.4
Name: mcp-superiorapis
Version: 1.1.9
Summary: This project is a Python-based **MCP Server** that dynamically fetches plugin definitions from **SuperiorAPIs** and auto-generates MCP tool functions based on OpenAPI schemas.
Author-email: marcus <marcus@cteam.com.tw>
Requires-Python: >=3.13
Requires-Dist: aiohttp>=3.11.0
Requires-Dist: mcp>=1.5.0
